SmarTFUzz/__init__.py
SmarTFUzz/main.py
SmarTFUzz/url_fuzzer.py
smartfuzz-0.0.5.dist-info/METADATA
smartfuzz-0.0.5.dist-info/WHEEL
smartfuzz-0.0.5.dist-info/entry_points.txt
smartfuzz-0.0.5.dist-info/RECORD
